mlneurotools/__init__.py
mlneurotools/features.py
mlneurotools/ml.py
mlneurotools/stats.py
mlneurotools/utils.py
mlneurotools-0.2.7.dist-info/LICENSE
mlneurotools-0.2.7.dist-info/METADATA
mlneurotools-0.2.7.dist-info/WHEEL
mlneurotools-0.2.7.dist-info/top_level.txt
mlneurotools-0.2.7.dist-info/RECORD
