Metadata-Version: 2.1
Name: mlneurotools
Version: 0.2.7
Summary: Tools for stats and ml
Home-page: http://github.com/arthurdehgan/NeuroPy-MLToolbox
Author: Arthur Dehgan
Author-email: arthur.dehgan@umontreal.ca
License: UNKNOWN
Platform: UNKNOWN
License-File: LICENSE
